nonebot_plugin_akashgen/__init__.py
nonebot_plugin_akashgen/api.py
nonebot_plugin_akashgen/config.py
nonebot_plugin_akashgen/handlers.py
nonebot_plugin_akashgen-0.1.1.dist-info/licenses/LICENSE
nonebot_plugin_akashgen-0.1.1.dist-info/METADATA
nonebot_plugin_akashgen-0.1.1.dist-info/WHEEL
nonebot_plugin_akashgen-0.1.1.dist-info/top_level.txt
nonebot_plugin_akashgen-0.1.1.dist-info/RECORD
