Metadata-Version: 2.4
Name: nonebot-plugin-akashgen
Version: 0.1.1
Summary: An FREE AI image generation plugin for NoneBot2 using Akash Network.
Author-email: 006lp <006lpsuki@gmail.com>
License: AGPL v3
Requires-Python: >=3.11
License-File: LICENSE
Requires-Dist: httpx>=0.28.1
Requires-Dist: nonebot-adapter-onebot>=2.4.6
Requires-Dist: nonebot2>=2.4.3
Dynamic: license-file
